genrepr.py
gen_repr-0.2.0.dist-info/LICENSE
gen_repr-0.2.0.dist-info/METADATA
gen_repr-0.2.0.dist-info/WHEEL
gen_repr-0.2.0.dist-info/top_level.txt
gen_repr-0.2.0.dist-info/RECORD
