Metadata-Version: 2.1
Name: gen-repr
Version: 0.2.0
Summary: Automatically generate the repr of a class with all it's fields
Home-page: https://github.com/Peter-Morawski/gen-repr
Author: Peter Morawski
Author-email: web@peter-morawski.de
License: MIT License
Keywords: make repr auto generate
Platform: UNKNOWN
Classifier: Development Status :: 4 - Beta
Classifier: License :: OSI Approved :: MIT License
Classifier: Operating System :: OS Independent
Classifier: Programming Language :: Python :: 2
Classifier: Programming Language :: Python :: 2.7
Classifier: Programming Language :: Python :: 3
Classifier: Programming Language :: Python :: 3.0
Classifier: Programming Language :: Python :: 3.1
Classifier: Programming Language :: Python :: 3.2
Classifier: Programming Language :: Python :: 3.3
Classifier: Programming Language :: Python :: 3.4
Classifier: Programming Language :: Python :: 3.5
Classifier: Programming Language :: Python :: 3.6
Classifier: Programming Language :: Python :: 3.7
Classifier: Programming Language :: Python :: 3.8
Classifier: Programming Language :: Python :: Implementation
Classifier: Topic :: Software Development :: Libraries
Classifier: Topic :: Software Development :: Widget Sets
Classifier: Topic :: Utilities
